odoo/addons/web_no_crawler/README.rst
odoo/addons/web_no_crawler/__init__.py
odoo/addons/web_no_crawler/__manifest__.py
odoo/addons/web_no_crawler/controllers/__init__.py
odoo/addons/web_no_crawler/controllers/main.py
odoo/addons/web_no_crawler/i18n/web_no_crawler.pot
odoo/addons/web_no_crawler/readme/CONTRIBUTORS.rst
odoo/addons/web_no_crawler/readme/CREDITS.rst
odoo/addons/web_no_crawler/readme/DESCRIPTION.rst
odoo/addons/web_no_crawler/readme/INSTALL.rst
odoo/addons/web_no_crawler/readme/ROADMAP.rst
odoo/addons/web_no_crawler/readme/USAGE.rst
odoo/addons/web_no_crawler/static/description/icon.png
odoo/addons/web_no_crawler/static/description/index.html
odoo12_addon_web_no_crawler-12.0.1.0.1.dist-info/METADATA
odoo12_addon_web_no_crawler-12.0.1.0.1.dist-info/WHEEL
odoo12_addon_web_no_crawler-12.0.1.0.1.dist-info/top_level.txt
odoo12_addon_web_no_crawler-12.0.1.0.1.dist-info/RECORD
